<?xml version="1.0" encoding="utf-8"?>
<?xml-stylesheet type="text/xsl" href="https://www.floatrates.com/currency-rates.xsl" ?>
<channel>
	<title>XML Historical Foreign Exchange Rates for Qatari Rial (QAR) (26 May 2017)</title>
	<link>http://www.floatrates.com/currency/qar/</link>
	<xmlLink>http://www.floatrates.com/daily/qar.xml</xmlLink>
	<description>XML historical foreign exchange rates for Qatari Rial (QAR) from the Float Rates. Published at 26 May 2017.</description>
	<language>en</language>
	<baseCurrency>QAR</baseCurrency>
	<pubDate>Fri, 26 May 2017</pubDate>
	<lastBuildDate>Fri, 26 May 2017</lastBuildDate>
	
	<item>
		<title>1 QAR = 0.245202 EUR</title>
		<link>http://www.floatrates.com/qar/eur/</link>
		<description>1 Qatari Rial = 0.245202 Euro</description>
		<pubDate></pubDate>
		<baseCurrency>QAR</baseCurrency>
		<baseName>Qatari Rial</baseName>
		<targetCurrency>EUR</targetCurrency>
		<targetName>Euro</targetName>
		<exchangeRate>0.245202</exchangeRate>
		<inverseRate>4.078275</inverseRate>
		<inverseDescription>1 Euro = 4.078275 Qatari Rial</inverseDescription>
	</item>
	<item>
		<title>1 QAR = 30.573767 JPY</title>
		<link>http://www.floatrates.com/qar/jpy/</link>
		<description>1 Qatari Rial = 30.573767 Japanese Yen</description>
		<pubDate></pubDate>
		<baseCurrency>QAR</baseCurrency>
		<baseName>Qatari Rial</baseName>
		<targetCurrency>JPY</targetCurrency>
		<targetName>Japanese Yen</targetName>
		<exchangeRate>30.573767</exchangeRate>
		<inverseRate>0.032708</inverseRate>
		<inverseDescription>1 Japanese Yen = 0.032708 Qatari Rial</inverseDescription>
	</item>
	<item>
		<title>1 QAR = 4.398374 ARS</title>
		<link>http://www.floatrates.com/qar/ars/</link>
		<description>1 Qatari Rial = 4.398374 Argentine Peso</description>
		<pubDate></pubDate>
		<baseCurrency>QAR</baseCurrency>
		<baseName>Qatari Rial</baseName>
		<targetCurrency>ARS</targetCurrency>
		<targetName>Argentine Peso</targetName>
		<exchangeRate>4.398374</exchangeRate>
		<inverseRate>0.227357</inverseRate>
		<inverseDescription>1 Argentine Peso = 0.227357 Qatari Rial</inverseDescription>
	</item>
	<item>
		<title>1 QAR = 0.369385 AUD</title>
		<link>http://www.floatrates.com/qar/aud/</link>
		<description>1 Qatari Rial = 0.369385 Australian Dollar</description>
		<pubDate></pubDate>
		<baseCurrency>QAR</baseCurrency>
		<baseName>Qatari Rial</baseName>
		<targetCurrency>AUD</targetCurrency>
		<targetName>Australian Dollar</targetName>
		<exchangeRate>0.369385</exchangeRate>
		<inverseRate>2.707201</inverseRate>
		<inverseDescription>1 Australian Dollar = 2.707201 Qatari Rial</inverseDescription>
	</item>
	<item>
		<title>1 QAR = 0.898553 BRL</title>
		<link>http://www.floatrates.com/qar/brl/</link>
		<description>1 Qatari Rial = 0.898553 Brazilian Real</description>
		<pubDate></pubDate>
		<baseCurrency>QAR</baseCurrency>
		<baseName>Qatari Rial</baseName>
		<targetCurrency>BRL</targetCurrency>
		<targetName>Brazilian Real</targetName>
		<exchangeRate>0.898553</exchangeRate>
		<inverseRate>1.112900</inverseRate>
		<inverseDescription>1 Brazilian Real = 1.112900 Qatari Rial</inverseDescription>
	</item>
	<item>
		<title>1 QAR = 0.370071 CAD</title>
		<link>http://www.floatrates.com/qar/cad/</link>
		<description>1 Qatari Rial = 0.370071 Canadian Dollar</description>
		<pubDate></pubDate>
		<baseCurrency>QAR</baseCurrency>
		<baseName>Qatari Rial</baseName>
		<targetCurrency>CAD</targetCurrency>
		<targetName>Canadian Dollar</targetName>
		<exchangeRate>0.370071</exchangeRate>
		<inverseRate>2.702188</inverseRate>
		<inverseDescription>1 Canadian Dollar = 2.702188 Qatari Rial</inverseDescription>
	</item>
	<item>
		<title>1 QAR = 183.909970 CLP</title>
		<link>http://www.floatrates.com/qar/clp/</link>
		<description>1 Qatari Rial = 183.909970 Chilean Peso</description>
		<pubDate></pubDate>
		<baseCurrency>QAR</baseCurrency>
		<baseName>Qatari Rial</baseName>
		<targetCurrency>CLP</targetCurrency>
		<targetName>Chilean Peso</targetName>
		<exchangeRate>183.909970</exchangeRate>
		<inverseRate>0.005437</inverseRate>
		<inverseDescription>1 Chilean Peso = 0.005437 Qatari Rial</inverseDescription>
	</item>
	<item>
		<title>1 QAR = 799.899923 COP</title>
		<link>http://www.floatrates.com/qar/cop/</link>
		<description>1 Qatari Rial = 799.899923 Colombian Peso</description>
		<pubDate></pubDate>
		<baseCurrency>QAR</baseCurrency>
		<baseName>Qatari Rial</baseName>
		<targetCurrency>COP</targetCurrency>
		<targetName>Colombian Peso</targetName>
		<exchangeRate>799.899923</exchangeRate>
		<inverseRate>0.001250</inverseRate>
		<inverseDescription>1 Colombian Peso = 0.001250 Qatari Rial</inverseDescription>
	</item>
	<item>
		<title>1 QAR = 307.386424 KRW</title>
		<link>http://www.floatrates.com/qar/krw/</link>
		<description>1 Qatari Rial = 307.386424 South Korean Won</description>
		<pubDate></pubDate>
		<baseCurrency>QAR</baseCurrency>
		<baseName>Qatari Rial</baseName>
		<targetCurrency>KRW</targetCurrency>
		<targetName>South Korean Won</targetName>
		<exchangeRate>307.386424</exchangeRate>
		<inverseRate>0.003253</inverseRate>
		<inverseDescription>1 South Korean Won = 0.003253 Qatari Rial</inverseDescription>
	</item>
	<item>
		<title>1 QAR = 1.825980 DKK</title>
		<link>http://www.floatrates.com/qar/dkk/</link>
		<description>1 Qatari Rial = 1.825980 Danish Krone</description>
		<pubDate></pubDate>
		<baseCurrency>QAR</baseCurrency>
		<baseName>Qatari Rial</baseName>
		<targetCurrency>DKK</targetCurrency>
		<targetName>Danish Krone</targetName>
		<exchangeRate>1.825980</exchangeRate>
		<inverseRate>0.547651</inverseRate>
		<inverseDescription>1 Danish Krone = 0.547651 Qatari Rial</inverseDescription>
	</item>
	<item>
		<title>1 QAR = 0.274725 USD</title>
		<link>http://www.floatrates.com/qar/usd/</link>
		<description>1 Qatari Rial = 0.274725 U.S. Dollar</description>
		<pubDate></pubDate>
		<baseCurrency>QAR</baseCurrency>
		<baseName>Qatari Rial</baseName>
		<targetCurrency>USD</targetCurrency>
		<targetName>U.S. Dollar</targetName>
		<exchangeRate>0.274725</exchangeRate>
		<inverseRate>3.640000</inverseRate>
		<inverseDescription>1 U.S. Dollar = 3.640000 Qatari Rial</inverseDescription>
	</item>
	<item>
		<title>1 QAR = 2.141062 HKD</title>
		<link>http://www.floatrates.com/qar/hkd/</link>
		<description>1 Qatari Rial = 2.141062 Hong Kong Dollar</description>
		<pubDate></pubDate>
		<baseCurrency>QAR</baseCurrency>
		<baseName>Qatari Rial</baseName>
		<targetCurrency>HKD</targetCurrency>
		<targetName>Hong Kong Dollar</targetName>
		<exchangeRate>2.141062</exchangeRate>
		<inverseRate>0.467058</inverseRate>
		<inverseDescription>1 Hong Kong Dollar = 0.467058 Qatari Rial</inverseDescription>
	</item>
	<item>
		<title>1 QAR = 17.740209 INR</title>
		<link>http://www.floatrates.com/qar/inr/</link>
		<description>1 Qatari Rial = 17.740209 Indian Rupee</description>
		<pubDate></pubDate>
		<baseCurrency>QAR</baseCurrency>
		<baseName>Qatari Rial</baseName>
		<targetCurrency>INR</targetCurrency>
		<targetName>Indian Rupee</targetName>
		<exchangeRate>17.740209</exchangeRate>
		<inverseRate>0.056369</inverseRate>
		<inverseDescription>1 Indian Rupee = 0.056369 Qatari Rial</inverseDescription>
	</item>
	<item>
		<title>1 QAR = 5.076176 MXN</title>
		<link>http://www.floatrates.com/qar/mxn/</link>
		<description>1 Qatari Rial = 5.076176 Mexican Peso</description>
		<pubDate></pubDate>
		<baseCurrency>QAR</baseCurrency>
		<baseName>Qatari Rial</baseName>
		<targetCurrency>MXN</targetCurrency>
		<targetName>Mexican Peso</targetName>
		<exchangeRate>5.076176</exchangeRate>
		<inverseRate>0.196999</inverseRate>
		<inverseDescription>1 Mexican Peso = 0.196999 Qatari Rial</inverseDescription>
	</item>
	<item>
		<title>1 QAR = 2.306869 NOK</title>
		<link>http://www.floatrates.com/qar/nok/</link>
		<description>1 Qatari Rial = 2.306869 Norwegian Krone</description>
		<pubDate></pubDate>
		<baseCurrency>QAR</baseCurrency>
		<baseName>Qatari Rial</baseName>
		<targetCurrency>NOK</targetCurrency>
		<targetName>Norwegian Krone</targetName>
		<exchangeRate>2.306869</exchangeRate>
		<inverseRate>0.433488</inverseRate>
		<inverseDescription>1 Norwegian Krone = 0.433488 Qatari Rial</inverseDescription>
	</item>
	<item>
		<title>1 QAR = 1,544.766709 PYG</title>
		<link>http://www.floatrates.com/qar/pyg/</link>
		<description>1 Qatari Rial = 1,544.766709 Paraguayan Guaraní</description>
		<pubDate></pubDate>
		<baseCurrency>QAR</baseCurrency>
		<baseName>Qatari Rial</baseName>
		<targetCurrency>PYG</targetCurrency>
		<targetName>Paraguayan Guaraní</targetName>
		<exchangeRate>1,544.766709</exchangeRate>
		<inverseRate>0.000647</inverseRate>
		<inverseDescription>1 Paraguayan Guaraní = 0.000647 Qatari Rial</inverseDescription>
	</item>
	<item>
		<title>1 QAR = 0.899449 PEN</title>
		<link>http://www.floatrates.com/qar/pen/</link>
		<description>1 Qatari Rial = 0.899449 Peruvian Nuevo Sol</description>
		<pubDate></pubDate>
		<baseCurrency>QAR</baseCurrency>
		<baseName>Qatari Rial</baseName>
		<targetCurrency>PEN</targetCurrency>
		<targetName>Peruvian Nuevo Sol</targetName>
		<exchangeRate>0.899449</exchangeRate>
		<inverseRate>1.111792</inverseRate>
		<inverseDescription>1 Peruvian Nuevo Sol = 1.111792 Qatari Rial</inverseDescription>
	</item>
	<item>
		<title>1 QAR = 0.213568 GBP</title>
		<link>http://www.floatrates.com/qar/gbp/</link>
		<description>1 Qatari Rial = 0.213568 U.K. Pound Sterling</description>
		<pubDate></pubDate>
		<baseCurrency>QAR</baseCurrency>
		<baseName>Qatari Rial</baseName>
		<targetCurrency>GBP</targetCurrency>
		<targetName>U.K. Pound Sterling</targetName>
		<exchangeRate>0.213568</exchangeRate>
		<inverseRate>4.682344</inverseRate>
		<inverseDescription>1 U.K. Pound Sterling = 4.682344 Qatari Rial</inverseDescription>
	</item>
	<item>
		<title>1 QAR = 0.380450 SGD</title>
		<link>http://www.floatrates.com/qar/sgd/</link>
		<description>1 Qatari Rial = 0.380450 Singapore Dollar</description>
		<pubDate></pubDate>
		<baseCurrency>QAR</baseCurrency>
		<baseName>Qatari Rial</baseName>
		<targetCurrency>SGD</targetCurrency>
		<targetName>Singapore Dollar</targetName>
		<exchangeRate>0.380450</exchangeRate>
		<inverseRate>2.628465</inverseRate>
		<inverseDescription>1 Singapore Dollar = 2.628465 Qatari Rial</inverseDescription>
	</item>
	<item>
		<title>1 QAR = 2.384817 SEK</title>
		<link>http://www.floatrates.com/qar/sek/</link>
		<description>1 Qatari Rial = 2.384817 Swedish Krona</description>
		<pubDate></pubDate>
		<baseCurrency>QAR</baseCurrency>
		<baseName>Qatari Rial</baseName>
		<targetCurrency>SEK</targetCurrency>
		<targetName>Swedish Krona</targetName>
		<exchangeRate>2.384817</exchangeRate>
		<inverseRate>0.419319</inverseRate>
		<inverseDescription>1 Swedish Krona = 0.419319 Qatari Rial</inverseDescription>
	</item>
	<item>
		<title>1 QAR = 0.266924 CHF</title>
		<link>http://www.floatrates.com/qar/chf/</link>
		<description>1 Qatari Rial = 0.266924 Swiss Franc</description>
		<pubDate></pubDate>
		<baseCurrency>QAR</baseCurrency>
		<baseName>Qatari Rial</baseName>
		<targetCurrency>CHF</targetCurrency>
		<targetName>Swiss Franc</targetName>
		<exchangeRate>0.266924</exchangeRate>
		<inverseRate>3.746385</inverseRate>
		<inverseDescription>1 Swiss Franc = 3.746385 Qatari Rial</inverseDescription>
	</item>
	<item>
		<title>1 QAR = 9.359923 THB</title>
		<link>http://www.floatrates.com/qar/thb/</link>
		<description>1 Qatari Rial = 9.359923 Thai Baht</description>
		<pubDate></pubDate>
		<baseCurrency>QAR</baseCurrency>
		<baseName>Qatari Rial</baseName>
		<targetCurrency>THB</targetCurrency>
		<targetName>Thai Baht</targetName>
		<exchangeRate>9.359923</exchangeRate>
		<inverseRate>0.106838</inverseRate>
		<inverseDescription>1 Thai Baht = 0.106838 Qatari Rial</inverseDescription>
	</item>
	<item>
		<title>1 QAR = 8.284192 TWD</title>
		<link>http://www.floatrates.com/qar/twd/</link>
		<description>1 Qatari Rial = 8.284192 New Taiwan Dollar </description>
		<pubDate></pubDate>
		<baseCurrency>QAR</baseCurrency>
		<baseName>Qatari Rial</baseName>
		<targetCurrency>TWD</targetCurrency>
		<targetName>New Taiwan Dollar </targetName>
		<exchangeRate>8.284192</exchangeRate>
		<inverseRate>0.120712</inverseRate>
		<inverseDescription>1 New Taiwan Dollar  = 0.120712 Qatari Rial</inverseDescription>
	</item>
	<item>
		<title>1 QAR = 7.755938 UYU</title>
		<link>http://www.floatrates.com/qar/uyu/</link>
		<description>1 Qatari Rial = 7.755938 Uruguayan Peso</description>
		<pubDate></pubDate>
		<baseCurrency>QAR</baseCurrency>
		<baseName>Qatari Rial</baseName>
		<targetCurrency>UYU</targetCurrency>
		<targetName>Uruguayan Peso</targetName>
		<exchangeRate>7.755938</exchangeRate>
		<inverseRate>0.128933</inverseRate>
		<inverseDescription>1 Uruguayan Peso = 0.128933 Qatari Rial</inverseDescription>
	</item>
	<item>
		<title>1 QAR = 2.740419 VEF</title>
		<link>http://www.floatrates.com/qar/vef/</link>
		<description>1 Qatari Rial = 2.740419 Venezuelan Bolivar (till 20 August 2018)</description>
		<pubDate></pubDate>
		<baseCurrency>QAR</baseCurrency>
		<baseName>Qatari Rial</baseName>
		<targetCurrency>VEF</targetCurrency>
		<targetName>Venezuelan Bolivar (till 20 August 2018)</targetName>
		<exchangeRate>2.740419</exchangeRate>
		<inverseRate>0.364908</inverseRate>
		<inverseDescription>1 Venezuelan Bolivar (till 20 August 2018) = 0.364908 Qatari Rial</inverseDescription>
	</item>
	<item>
		<title>1 QAR = 1.884615 BOB</title>
		<link>http://www.floatrates.com/qar/bob/</link>
		<description>1 Qatari Rial = 1.884615 Bolivian Boliviano</description>
		<pubDate></pubDate>
		<baseCurrency>QAR</baseCurrency>
		<baseName>Qatari Rial</baseName>
		<targetCurrency>BOB</targetCurrency>
		<targetName>Bolivian Boliviano</targetName>
		<exchangeRate>1.884615</exchangeRate>
		<inverseRate>0.530612</inverseRate>
		<inverseDescription>1 Bolivian Boliviano = 0.530612 Qatari Rial</inverseDescription>
	</item>
	<item>
		<title>1 QAR = 8.215000 NIO</title>
		<link>http://www.floatrates.com/qar/nio/</link>
		<description>1 Qatari Rial = 8.215000 Nicaraguan Córdoba</description>
		<pubDate></pubDate>
		<baseCurrency>QAR</baseCurrency>
		<baseName>Qatari Rial</baseName>
		<targetCurrency>NIO</targetCurrency>
		<targetName>Nicaraguan Córdoba</targetName>
		<exchangeRate>8.215000</exchangeRate>
		<inverseRate>0.121729</inverseRate>
		<inverseDescription>1 Nicaraguan Córdoba = 0.121729 Qatari Rial</inverseDescription>
	</item>
	<item>
		<title>1 QAR = 1.884056 CNY</title>
		<link>http://www.floatrates.com/qar/cny/</link>
		<description>1 Qatari Rial = 1.884056 Chinese Yuan</description>
		<pubDate></pubDate>
		<baseCurrency>QAR</baseCurrency>
		<baseName>Qatari Rial</baseName>
		<targetCurrency>CNY</targetCurrency>
		<targetName>Chinese Yuan</targetName>
		<exchangeRate>1.884056</exchangeRate>
		<inverseRate>0.530770</inverseRate>
		<inverseDescription>1 Chinese Yuan = 0.530770 Qatari Rial</inverseDescription>
	</item>
	<item>
		<title>1 QAR = 0.390777 NZD</title>
		<link>http://www.floatrates.com/qar/nzd/</link>
		<description>1 Qatari Rial = 0.390777 New Zealand Dollar</description>
		<pubDate></pubDate>
		<baseCurrency>QAR</baseCurrency>
		<baseName>Qatari Rial</baseName>
		<targetCurrency>NZD</targetCurrency>
		<targetName>New Zealand Dollar</targetName>
		<exchangeRate>0.390777</exchangeRate>
		<inverseRate>2.559005</inverseRate>
		<inverseDescription>1 New Zealand Dollar = 2.559005 Qatari Rial</inverseDescription>
	</item>
	<item>
		<title>1 QAR = 1.174580 MYR</title>
		<link>http://www.floatrates.com/qar/myr/</link>
		<description>1 Qatari Rial = 1.174580 Malaysian Ringgit</description>
		<pubDate></pubDate>
		<baseCurrency>QAR</baseCurrency>
		<baseName>Qatari Rial</baseName>
		<targetCurrency>MYR</targetCurrency>
		<targetName>Malaysian Ringgit</targetName>
		<exchangeRate>1.174580</exchangeRate>
		<inverseRate>0.851368</inverseRate>
		<inverseDescription>1 Malaysian Ringgit = 0.851368 Qatari Rial</inverseDescription>
	</item>
	<item>
		<title>1 QAR = 3,652.983983 IDR</title>
		<link>http://www.floatrates.com/qar/idr/</link>
		<description>1 Qatari Rial = 3,652.983983 Indonesian Rupiah</description>
		<pubDate></pubDate>
		<baseCurrency>QAR</baseCurrency>
		<baseName>Qatari Rial</baseName>
		<targetCurrency>IDR</targetCurrency>
		<targetName>Indonesian Rupiah</targetName>
		<exchangeRate>3,652.983983</exchangeRate>
		<inverseRate>0.000274</inverseRate>
		<inverseDescription>1 Indonesian Rupiah = 0.000274 Qatari Rial</inverseDescription>
	</item>
	<item>
		<title>1 QAR = 6,243.118012 VND</title>
		<link>http://www.floatrates.com/qar/vnd/</link>
		<description>1 Qatari Rial = 6,243.118012 Vietnamese Dong</description>
		<pubDate></pubDate>
		<baseCurrency>QAR</baseCurrency>
		<baseName>Qatari Rial</baseName>
		<targetCurrency>VND</targetCurrency>
		<targetName>Vietnamese Dong</targetName>
		<exchangeRate>6,243.118012</exchangeRate>
		<inverseRate>0.000160</inverseRate>
		<inverseDescription>1 Vietnamese Dong = 0.000160 Qatari Rial</inverseDescription>
	</item>
	<item>
		<title>1 QAR = 0.873541 PGK</title>
		<link>http://www.floatrates.com/qar/pgk/</link>
		<description>1 Qatari Rial = 0.873541 Papua New Guinean kina</description>
		<pubDate></pubDate>
		<baseCurrency>QAR</baseCurrency>
		<baseName>Qatari Rial</baseName>
		<targetCurrency>PGK</targetCurrency>
		<targetName>Papua New Guinean kina</targetName>
		<exchangeRate>0.873541</exchangeRate>
		<inverseRate>1.144765</inverseRate>
		<inverseDescription>1 Papua New Guinean kina = 1.144765 Qatari Rial</inverseDescription>
	</item>
	<item>
		<title>1 QAR = 1.008931 AED</title>
		<link>http://www.floatrates.com/qar/aed/</link>
		<description>1 Qatari Rial = 1.008931 U.A.E Dirham</description>
		<pubDate></pubDate>
		<baseCurrency>QAR</baseCurrency>
		<baseName>Qatari Rial</baseName>
		<targetCurrency>AED</targetCurrency>
		<targetName>U.A.E Dirham</targetName>
		<exchangeRate>1.008931</exchangeRate>
		<inverseRate>0.991148</inverseRate>
		<inverseDescription>1 U.A.E Dirham = 0.991148 Qatari Rial</inverseDescription>
	</item>
	<item>
		<title>1 QAR = 0.981813 ILS</title>
		<link>http://www.floatrates.com/qar/ils/</link>
		<description>1 Qatari Rial = 0.981813 Israeli New Sheqel</description>
		<pubDate></pubDate>
		<baseCurrency>QAR</baseCurrency>
		<baseName>Qatari Rial</baseName>
		<targetCurrency>ILS</targetCurrency>
		<targetName>Israeli New Sheqel</targetName>
		<exchangeRate>0.981813</exchangeRate>
		<inverseRate>1.018524</inverseRate>
		<inverseDescription>1 Israeli New Sheqel = 1.018524 Qatari Rial</inverseDescription>
	</item>
	<item>
		<title>1 QAR = 3.537768 ZAR</title>
		<link>http://www.floatrates.com/qar/zar/</link>
		<description>1 Qatari Rial = 3.537768 South African Rand</description>
		<pubDate></pubDate>
		<baseCurrency>QAR</baseCurrency>
		<baseName>Qatari Rial</baseName>
		<targetCurrency>ZAR</targetCurrency>
		<targetName>South African Rand</targetName>
		<exchangeRate>3.537768</exchangeRate>
		<inverseRate>0.282664</inverseRate>
		<inverseDescription>1 South African Rand = 0.282664 Qatari Rial</inverseDescription>
	</item>
	<item>
		<title>1 QAR = 0.194939 JOD</title>
		<link>http://www.floatrates.com/qar/jod/</link>
		<description>1 Qatari Rial = 0.194939 Jordanian Dinar</description>
		<pubDate></pubDate>
		<baseCurrency>QAR</baseCurrency>
		<baseName>Qatari Rial</baseName>
		<targetCurrency>JOD</targetCurrency>
		<targetName>Jordanian Dinar</targetName>
		<exchangeRate>0.194939</exchangeRate>
		<inverseRate>5.129813</inverseRate>
		<inverseDescription>1 Jordanian Dinar = 5.129813 Qatari Rial</inverseDescription>
	</item>
	<item>
		<title>1 QAR = 414.290351 LBP</title>
		<link>http://www.floatrates.com/qar/lbp/</link>
		<description>1 Qatari Rial = 414.290351 Lebanese Pound</description>
		<pubDate></pubDate>
		<baseCurrency>QAR</baseCurrency>
		<baseName>Qatari Rial</baseName>
		<targetCurrency>LBP</targetCurrency>
		<targetName>Lebanese Pound</targetName>
		<exchangeRate>414.290351</exchangeRate>
		<inverseRate>0.002414</inverseRate>
		<inverseDescription>1 Lebanese Pound = 0.002414 Qatari Rial</inverseDescription>
	</item>
	<item>
		<title>1 QAR = 4.963071 EGP</title>
		<link>http://www.floatrates.com/qar/egp/</link>
		<description>1 Qatari Rial = 4.963071 Egyptian Pound</description>
		<pubDate></pubDate>
		<baseCurrency>QAR</baseCurrency>
		<baseName>Qatari Rial</baseName>
		<targetCurrency>EGP</targetCurrency>
		<targetName>Egyptian Pound</targetName>
		<exchangeRate>4.963071</exchangeRate>
		<inverseRate>0.201488</inverseRate>
		<inverseDescription>1 Egyptian Pound = 0.201488 Qatari Rial</inverseDescription>
	</item>
	<item>
		<title>1 QAR = 0.464286 AZN</title>
		<link>http://www.floatrates.com/qar/azn/</link>
		<description>1 Qatari Rial = 0.464286 Azerbaijan Manat</description>
		<pubDate></pubDate>
		<baseCurrency>QAR</baseCurrency>
		<baseName>Qatari Rial</baseName>
		<targetCurrency>AZN</targetCurrency>
		<targetName>Azerbaijan Manat</targetName>
		<exchangeRate>0.464286</exchangeRate>
		<inverseRate>2.153844</inverseRate>
		<inverseDescription>1 Azerbaijan Manat = 2.153844 Qatari Rial</inverseDescription>
	</item>
	<item>
		<title>1 QAR = 132.967558 AMD</title>
		<link>http://www.floatrates.com/qar/amd/</link>
		<description>1 Qatari Rial = 132.967558 Armenia Dram</description>
		<pubDate></pubDate>
		<baseCurrency>QAR</baseCurrency>
		<baseName>Qatari Rial</baseName>
		<targetCurrency>AMD</targetCurrency>
		<targetName>Armenia Dram</targetName>
		<exchangeRate>132.967558</exchangeRate>
		<inverseRate>0.007521</inverseRate>
		<inverseDescription>1 Armenia Dram = 0.007521 Qatari Rial</inverseDescription>
	</item>
	<item>
		<title>1 QAR = 0.510619 BYN</title>
		<link>http://www.floatrates.com/qar/byn/</link>
		<description>1 Qatari Rial = 0.510619 Belarussian Ruble</description>
		<pubDate></pubDate>
		<baseCurrency>QAR</baseCurrency>
		<baseName>Qatari Rial</baseName>
		<targetCurrency>BYN</targetCurrency>
		<targetName>Belarussian Ruble</targetName>
		<exchangeRate>0.510619</exchangeRate>
		<inverseRate>1.958409</inverseRate>
		<inverseDescription>1 Belarussian Ruble = 1.958409 Qatari Rial</inverseDescription>
	</item>
	<item>
		<title>1 QAR = 0.479757 BGN</title>
		<link>http://www.floatrates.com/qar/bgn/</link>
		<description>1 Qatari Rial = 0.479757 Bulgarian Lev</description>
		<pubDate></pubDate>
		<baseCurrency>QAR</baseCurrency>
		<baseName>Qatari Rial</baseName>
		<targetCurrency>BGN</targetCurrency>
		<targetName>Bulgarian Lev</targetName>
		<exchangeRate>0.479757</exchangeRate>
		<inverseRate>2.084390</inverseRate>
		<inverseDescription>1 Bulgarian Lev = 2.084390 Qatari Rial</inverseDescription>
	</item>
	<item>
		<title>1 QAR = 75.287009 HUF</title>
		<link>http://www.floatrates.com/qar/huf/</link>
		<description>1 Qatari Rial = 75.287009 Hungarian Forint</description>
		<pubDate></pubDate>
		<baseCurrency>QAR</baseCurrency>
		<baseName>Qatari Rial</baseName>
		<targetCurrency>HUF</targetCurrency>
		<targetName>Hungarian Forint</targetName>
		<exchangeRate>75.287009</exchangeRate>
		<inverseRate>0.013283</inverseRate>
		<inverseDescription>1 Hungarian Forint = 0.013283 Qatari Rial</inverseDescription>
	</item>
	<item>
		<title>1 QAR = 85.598990 KZT</title>
		<link>http://www.floatrates.com/qar/kzt/</link>
		<description>1 Qatari Rial = 85.598990 Kazakhstani Tenge</description>
		<pubDate></pubDate>
		<baseCurrency>QAR</baseCurrency>
		<baseName>Qatari Rial</baseName>
		<targetCurrency>KZT</targetCurrency>
		<targetName>Kazakhstani Tenge</targetName>
		<exchangeRate>85.598990</exchangeRate>
		<inverseRate>0.011682</inverseRate>
		<inverseDescription>1 Kazakhstani Tenge = 0.011682 Qatari Rial</inverseDescription>
	</item>
	<item>
		<title>1 QAR = 18.674451 KGS</title>
		<link>http://www.floatrates.com/qar/kgs/</link>
		<description>1 Qatari Rial = 18.674451 Kyrgyzstan Som</description>
		<pubDate></pubDate>
		<baseCurrency>QAR</baseCurrency>
		<baseName>Qatari Rial</baseName>
		<targetCurrency>KGS</targetCurrency>
		<targetName>Kyrgyzstan Som</targetName>
		<exchangeRate>18.674451</exchangeRate>
		<inverseRate>0.053549</inverseRate>
		<inverseDescription>1 Kyrgyzstan Som = 0.053549 Qatari Rial</inverseDescription>
	</item>
	<item>
		<title>1 QAR = 5.013462 MDL</title>
		<link>http://www.floatrates.com/qar/mdl/</link>
		<description>1 Qatari Rial = 5.013462 Moldova Lei</description>
		<pubDate></pubDate>
		<baseCurrency>QAR</baseCurrency>
		<baseName>Qatari Rial</baseName>
		<targetCurrency>MDL</targetCurrency>
		<targetName>Moldova Lei</targetName>
		<exchangeRate>5.013462</exchangeRate>
		<inverseRate>0.199463</inverseRate>
		<inverseDescription>1 Moldova Lei = 0.199463 Qatari Rial</inverseDescription>
	</item>
	<item>
		<title>1 QAR = 0.960437 TMT</title>
		<link>http://www.floatrates.com/qar/tmt/</link>
		<description>1 Qatari Rial = 0.960437 New Turkmenistan Manat</description>
		<pubDate></pubDate>
		<baseCurrency>QAR</baseCurrency>
		<baseName>Qatari Rial</baseName>
		<targetCurrency>TMT</targetCurrency>
		<targetName>New Turkmenistan Manat</targetName>
		<exchangeRate>0.960437</exchangeRate>
		<inverseRate>1.041193</inverseRate>
		<inverseDescription>1 New Turkmenistan Manat = 1.041193 Qatari Rial</inverseDescription>
	</item>
	<item>
		<title>1 QAR = 1.024303 PLN</title>
		<link>http://www.floatrates.com/qar/pln/</link>
		<description>1 Qatari Rial = 1.024303 Polish Zloty</description>
		<pubDate></pubDate>
		<baseCurrency>QAR</baseCurrency>
		<baseName>Qatari Rial</baseName>
		<targetCurrency>PLN</targetCurrency>
		<targetName>Polish Zloty</targetName>
		<exchangeRate>1.024303</exchangeRate>
		<inverseRate>0.976274</inverseRate>
		<inverseDescription>1 Polish Zloty = 0.976274 Qatari Rial</inverseDescription>
	</item>
	<item>
		<title>1 QAR = 1.117745 RON</title>
		<link>http://www.floatrates.com/qar/ron/</link>
		<description>1 Qatari Rial = 1.117745 Romanian New Leu</description>
		<pubDate></pubDate>
		<baseCurrency>QAR</baseCurrency>
		<baseName>Qatari Rial</baseName>
		<targetCurrency>RON</targetCurrency>
		<targetName>Romanian New Leu</targetName>
		<exchangeRate>1.117745</exchangeRate>
		<inverseRate>0.894659</inverseRate>
		<inverseDescription>1 Romanian New Leu = 0.894659 Qatari Rial</inverseDescription>
	</item>
	<item>
		<title>1 QAR = 2.418957 TJS</title>
		<link>http://www.floatrates.com/qar/tjs/</link>
		<description>1 Qatari Rial = 2.418957 Tajikistan Ruble</description>
		<pubDate></pubDate>
		<baseCurrency>QAR</baseCurrency>
		<baseName>Qatari Rial</baseName>
		<targetCurrency>TJS</targetCurrency>
		<targetName>Tajikistan Ruble</targetName>
		<exchangeRate>2.418957</exchangeRate>
		<inverseRate>0.413401</inverseRate>
		<inverseDescription>1 Tajikistan Ruble = 0.413401 Qatari Rial</inverseDescription>
	</item>
	<item>
		<title>1 QAR = 0.980788 TRY</title>
		<link>http://www.floatrates.com/qar/try/</link>
		<description>1 Qatari Rial = 0.980788 Turkish Lira</description>
		<pubDate></pubDate>
		<baseCurrency>QAR</baseCurrency>
		<baseName>Qatari Rial</baseName>
		<targetCurrency>TRY</targetCurrency>
		<targetName>Turkish Lira</targetName>
		<exchangeRate>0.980788</exchangeRate>
		<inverseRate>1.019589</inverseRate>
		<inverseDescription>1 Turkish Lira = 1.019589 Qatari Rial</inverseDescription>
	</item>
	<item>
		<title>1 QAR = 1,049.577114 UZS</title>
		<link>http://www.floatrates.com/qar/uzs/</link>
		<description>1 Qatari Rial = 1,049.577114 Uzbekistan Sum</description>
		<pubDate></pubDate>
		<baseCurrency>QAR</baseCurrency>
		<baseName>Qatari Rial</baseName>
		<targetCurrency>UZS</targetCurrency>
		<targetName>Uzbekistan Sum</targetName>
		<exchangeRate>1,049.577114</exchangeRate>
		<inverseRate>0.000953</inverseRate>
		<inverseDescription>1 Uzbekistan Sum = 0.000953 Qatari Rial</inverseDescription>
	</item>
	<item>
		<title>1 QAR = 7.241588 UAH</title>
		<link>http://www.floatrates.com/qar/uah/</link>
		<description>1 Qatari Rial = 7.241588 Ukrainian Hryvnia</description>
		<pubDate></pubDate>
		<baseCurrency>QAR</baseCurrency>
		<baseName>Qatari Rial</baseName>
		<targetCurrency>UAH</targetCurrency>
		<targetName>Ukrainian Hryvnia</targetName>
		<exchangeRate>7.241588</exchangeRate>
		<inverseRate>0.138091</inverseRate>
		<inverseDescription>1 Ukrainian Hryvnia = 0.138091 Qatari Rial</inverseDescription>
	</item>
	<item>
		<title>1 QAR = 6.484791 CZK</title>
		<link>http://www.floatrates.com/qar/czk/</link>
		<description>1 Qatari Rial = 6.484791 Czech Koruna</description>
		<pubDate></pubDate>
		<baseCurrency>QAR</baseCurrency>
		<baseName>Qatari Rial</baseName>
		<targetCurrency>CZK</targetCurrency>
		<targetName>Czech Koruna</targetName>
		<exchangeRate>6.484791</exchangeRate>
		<inverseRate>0.154207</inverseRate>
		<inverseDescription>1 Czech Koruna = 0.154207 Qatari Rial</inverseDescription>
	</item>
	<item>
		<title>1 QAR = 15.609820 RUB</title>
		<link>http://www.floatrates.com/qar/rub/</link>
		<description>1 Qatari Rial = 15.609820 Russian Rouble</description>
		<pubDate></pubDate>
		<baseCurrency>QAR</baseCurrency>
		<baseName>Qatari Rial</baseName>
		<targetCurrency>RUB</targetCurrency>
		<targetName>Russian Rouble</targetName>
		<exchangeRate>15.609820</exchangeRate>
		<inverseRate>0.064062</inverseRate>
		<inverseDescription>1 Russian Rouble = 0.064062 Qatari Rial</inverseDescription>
	</item>
	<item>
		<title>1 QAR = 1.821464 HRK</title>
		<link>http://www.floatrates.com/qar/hrk/</link>
		<description>1 Qatari Rial = 1.821464 Croatian Kuna</description>
		<pubDate></pubDate>
		<baseCurrency>QAR</baseCurrency>
		<baseName>Qatari Rial</baseName>
		<targetCurrency>HRK</targetCurrency>
		<targetName>Croatian Kuna</targetName>
		<exchangeRate>1.821464</exchangeRate>
		<inverseRate>0.549009</inverseRate>
		<inverseDescription>1 Croatian Kuna = 0.549009 Qatari Rial</inverseDescription>
	</item>
	<item>
		<title>1 QAR = 30.094636 RSD</title>
		<link>http://www.floatrates.com/qar/rsd/</link>
		<description>1 Qatari Rial = 30.094636 Serbian Dinar</description>
		<pubDate></pubDate>
		<baseCurrency>QAR</baseCurrency>
		<baseName>Qatari Rial</baseName>
		<targetCurrency>RSD</targetCurrency>
		<targetName>Serbian Dinar</targetName>
		<exchangeRate>30.094636</exchangeRate>
		<inverseRate>0.033229</inverseRate>
		<inverseDescription>1 Serbian Dinar = 0.033229 Qatari Rial</inverseDescription>
	</item>
	<item>
		<title>1 QAR = 29.822280 DZD</title>
		<link>http://www.floatrates.com/qar/dzd/</link>
		<description>1 Qatari Rial = 29.822280 Algerian Dinar</description>
		<pubDate></pubDate>
		<baseCurrency>QAR</baseCurrency>
		<baseName>Qatari Rial</baseName>
		<targetCurrency>DZD</targetCurrency>
		<targetName>Algerian Dinar</targetName>
		<exchangeRate>29.822280</exchangeRate>
		<inverseRate>0.033532</inverseRate>
		<inverseDescription>1 Algerian Dinar = 0.033532 Qatari Rial</inverseDescription>
	</item>
	<item>
		<title>1 QAR = 0.103297 BHD</title>
		<link>http://www.floatrates.com/qar/bhd/</link>
		<description>1 Qatari Rial = 0.103297 Bahrain Dinar</description>
		<pubDate></pubDate>
		<baseCurrency>QAR</baseCurrency>
		<baseName>Qatari Rial</baseName>
		<targetCurrency>BHD</targetCurrency>
		<targetName>Bahrain Dinar</targetName>
		<exchangeRate>0.103297</exchangeRate>
		<inverseRate>9.680851</inverseRate>
		<inverseDescription>1 Bahrain Dinar = 9.680851 Qatari Rial</inverseDescription>
	</item>
	<item>
		<title>1 QAR = 2.800462 BWP</title>
		<link>http://www.floatrates.com/qar/bwp/</link>
		<description>1 Qatari Rial = 2.800462 Botswana Pula</description>
		<pubDate></pubDate>
		<baseCurrency>QAR</baseCurrency>
		<baseName>Qatari Rial</baseName>
		<targetCurrency>BWP</targetCurrency>
		<targetName>Botswana Pula</targetName>
		<exchangeRate>2.800462</exchangeRate>
		<inverseRate>0.357084</inverseRate>
		<inverseDescription>1 Botswana Pula = 0.357084 Qatari Rial</inverseDescription>
	</item>
	<item>
		<title>1 QAR = 0.380714 BND</title>
		<link>http://www.floatrates.com/qar/bnd/</link>
		<description>1 Qatari Rial = 0.380714 Brunei Dollar</description>
		<pubDate></pubDate>
		<baseCurrency>QAR</baseCurrency>
		<baseName>Qatari Rial</baseName>
		<targetCurrency>BND</targetCurrency>
		<targetName>Brunei Dollar</targetName>
		<exchangeRate>0.380714</exchangeRate>
		<inverseRate>2.626642</inverseRate>
		<inverseDescription>1 Brunei Dollar = 2.626642 Qatari Rial</inverseDescription>
	</item>
	<item>
		<title>1 QAR = 27.543956 ISK</title>
		<link>http://www.floatrates.com/qar/isk/</link>
		<description>1 Qatari Rial = 27.543956 Icelandic Krona</description>
		<pubDate></pubDate>
		<baseCurrency>QAR</baseCurrency>
		<baseName>Qatari Rial</baseName>
		<targetCurrency>ISK</targetCurrency>
		<targetName>Icelandic Krona</targetName>
		<exchangeRate>27.543956</exchangeRate>
		<inverseRate>0.036306</inverseRate>
		<inverseDescription>1 Icelandic Krona = 0.036306 Qatari Rial</inverseDescription>
	</item>
	<item>
		<title>1 QAR = 0.083338 KWD</title>
		<link>http://www.floatrates.com/qar/kwd/</link>
		<description>1 Qatari Rial = 0.083338 Kuwaiti Dinar</description>
		<pubDate></pubDate>
		<baseCurrency>QAR</baseCurrency>
		<baseName>Qatari Rial</baseName>
		<targetCurrency>KWD</targetCurrency>
		<targetName>Kuwaiti Dinar</targetName>
		<exchangeRate>0.083338</exchangeRate>
		<inverseRate>11.999341</inverseRate>
		<inverseDescription>1 Kuwaiti Dinar = 11.999341 Qatari Rial</inverseDescription>
	</item>
	<item>
		<title>1 QAR = 0.198568 LYD</title>
		<link>http://www.floatrates.com/qar/lyd/</link>
		<description>1 Qatari Rial = 0.198568 Libyan Dinar</description>
		<pubDate></pubDate>
		<baseCurrency>QAR</baseCurrency>
		<baseName>Qatari Rial</baseName>
		<targetCurrency>LYD</targetCurrency>
		<targetName>Libyan Dinar</targetName>
		<exchangeRate>0.198568</exchangeRate>
		<inverseRate>5.036049</inverseRate>
		<inverseDescription>1 Libyan Dinar = 5.036049 Qatari Rial</inverseDescription>
	</item>
	<item>
		<title>1 QAR = 9.530082 MUR</title>
		<link>http://www.floatrates.com/qar/mur/</link>
		<description>1 Qatari Rial = 9.530082 Mauritian Rupee</description>
		<pubDate></pubDate>
		<baseCurrency>QAR</baseCurrency>
		<baseName>Qatari Rial</baseName>
		<targetCurrency>MUR</targetCurrency>
		<targetName>Mauritian Rupee</targetName>
		<exchangeRate>9.530082</exchangeRate>
		<inverseRate>0.104931</inverseRate>
		<inverseDescription>1 Mauritian Rupee = 0.104931 Qatari Rial</inverseDescription>
	</item>
	<item>
		<title>1 QAR = 28.376374 NPR</title>
		<link>http://www.floatrates.com/qar/npr/</link>
		<description>1 Qatari Rial = 28.376374 Nepalese Rupee</description>
		<pubDate></pubDate>
		<baseCurrency>QAR</baseCurrency>
		<baseName>Qatari Rial</baseName>
		<targetCurrency>NPR</targetCurrency>
		<targetName>Nepalese Rupee</targetName>
		<exchangeRate>28.376374</exchangeRate>
		<inverseRate>0.035241</inverseRate>
		<inverseDescription>1 Nepalese Rupee = 0.035241 Qatari Rial</inverseDescription>
	</item>
	<item>
		<title>1 QAR = 0.105632 OMR</title>
		<link>http://www.floatrates.com/qar/omr/</link>
		<description>1 Qatari Rial = 0.105632 Omani Rial</description>
		<pubDate></pubDate>
		<baseCurrency>QAR</baseCurrency>
		<baseName>Qatari Rial</baseName>
		<targetCurrency>OMR</targetCurrency>
		<targetName>Omani Rial</targetName>
		<exchangeRate>0.105632</exchangeRate>
		<inverseRate>9.466840</inverseRate>
		<inverseDescription>1 Omani Rial = 9.466840 Qatari Rial</inverseDescription>
	</item>
	<item>
		<title>1 QAR = 28.810852 PKR</title>
		<link>http://www.floatrates.com/qar/pkr/</link>
		<description>1 Qatari Rial = 28.810852 Pakistani Rupee</description>
		<pubDate></pubDate>
		<baseCurrency>QAR</baseCurrency>
		<baseName>Qatari Rial</baseName>
		<targetCurrency>PKR</targetCurrency>
		<targetName>Pakistani Rupee</targetName>
		<exchangeRate>28.810852</exchangeRate>
		<inverseRate>0.034709</inverseRate>
		<inverseDescription>1 Pakistani Rupee = 0.034709 Qatari Rial</inverseDescription>
	</item>
	<item>
		<title>1 QAR = 1.000000 QAR</title>
		<link>http://www.floatrates.com/qar/qar/</link>
		<description>1 Qatari Rial = 1.000000 Qatari Rial</description>
		<pubDate></pubDate>
		<baseCurrency>QAR</baseCurrency>
		<baseName>Qatari Rial</baseName>
		<targetCurrency>QAR</targetCurrency>
		<targetName>Qatari Rial</targetName>
		<exchangeRate>1.000000</exchangeRate>
		<inverseRate>1.000000</inverseRate>
		<inverseDescription>1 Qatari Rial = 1.000000 Qatari Rial</inverseDescription>
	</item>
	<item>
		<title>1 QAR = 1.030220 SAR</title>
		<link>http://www.floatrates.com/qar/sar/</link>
		<description>1 Qatari Rial = 1.030220 Saudi Riyal</description>
		<pubDate></pubDate>
		<baseCurrency>QAR</baseCurrency>
		<baseName>Qatari Rial</baseName>
		<targetCurrency>SAR</targetCurrency>
		<targetName>Saudi Riyal</targetName>
		<exchangeRate>1.030220</exchangeRate>
		<inverseRate>0.970666</inverseRate>
		<inverseDescription>1 Saudi Riyal = 0.970666 Qatari Rial</inverseDescription>
	</item>
	<item>
		<title>1 QAR = 41.895604 LKR</title>
		<link>http://www.floatrates.com/qar/lkr/</link>
		<description>1 Qatari Rial = 41.895604 Sri Lanka Rupee</description>
		<pubDate></pubDate>
		<baseCurrency>QAR</baseCurrency>
		<baseName>Qatari Rial</baseName>
		<targetCurrency>LKR</targetCurrency>
		<targetName>Sri Lanka Rupee</targetName>
		<exchangeRate>41.895604</exchangeRate>
		<inverseRate>0.023869</inverseRate>
		<inverseDescription>1 Sri Lanka Rupee = 0.023869 Qatari Rial</inverseDescription>
	</item>
	<item>
		<title>1 QAR = 1.853874 TTD</title>
		<link>http://www.floatrates.com/qar/ttd/</link>
		<description>1 Qatari Rial = 1.853874 Trinidad Tobago Dollar</description>
		<pubDate></pubDate>
		<baseCurrency>QAR</baseCurrency>
		<baseName>Qatari Rial</baseName>
		<targetCurrency>TTD</targetCurrency>
		<targetName>Trinidad Tobago Dollar</targetName>
		<exchangeRate>1.853874</exchangeRate>
		<inverseRate>0.539411</inverseRate>
		<inverseDescription>1 Trinidad Tobago Dollar = 0.539411 Qatari Rial</inverseDescription>
	</item>
	<item>
		<title>1 QAR = 0.669398 TND</title>
		<link>http://www.floatrates.com/qar/tnd/</link>
		<description>1 Qatari Rial = 0.669398 Tunisian Dinar</description>
		<pubDate></pubDate>
		<baseCurrency>QAR</baseCurrency>
		<baseName>Qatari Rial</baseName>
		<targetCurrency>TND</targetCurrency>
		<targetName>Tunisian Dinar</targetName>
		<exchangeRate>0.669398</exchangeRate>
		<inverseRate>1.493879</inverseRate>
		<inverseDescription>1 Tunisian Dinar = 1.493879 Qatari Rial</inverseDescription>
	</item>
	<item>
		<title>1 QAR = 0.549451 BBD</title>
		<link>http://www.floatrates.com/qar/bbd/</link>
		<description>1 Qatari Rial = 0.549451 Barbadian Dollar</description>
		<pubDate></pubDate>
		<baseCurrency>QAR</baseCurrency>
		<baseName>Qatari Rial</baseName>
		<targetCurrency>BBD</targetCurrency>
		<targetName>Barbadian Dollar</targetName>
		<exchangeRate>0.549451</exchangeRate>
		<inverseRate>1.820000</inverseRate>
		<inverseDescription>1 Barbadian Dollar = 1.820000 Qatari Rial</inverseDescription>
	</item>
	<item>
		<title>1 QAR = 13.674674 PHP</title>
		<link>http://www.floatrates.com/qar/php/</link>
		<description>1 Qatari Rial = 13.674674 Philippine Peso</description>
		<pubDate></pubDate>
		<baseCurrency>QAR</baseCurrency>
		<baseName>Qatari Rial</baseName>
		<targetCurrency>PHP</targetCurrency>
		<targetName>Philippine Peso</targetName>
		<exchangeRate>13.674674</exchangeRate>
		<inverseRate>0.073128</inverseRate>
		<inverseDescription>1 Philippine Peso = 0.073128 Qatari Rial</inverseDescription>
	</item>
	<item>
		<title>1 QAR = 160.988759 XAF</title>
		<link>http://www.floatrates.com/qar/xaf/</link>
		<description>1 Qatari Rial = 160.988759 Central African CFA Franc</description>
		<pubDate></pubDate>
		<baseCurrency>QAR</baseCurrency>
		<baseName>Qatari Rial</baseName>
		<targetCurrency>XAF</targetCurrency>
		<targetName>Central African CFA Franc</targetName>
		<exchangeRate>160.988759</exchangeRate>
		<inverseRate>0.006212</inverseRate>
		<inverseDescription>1 Central African CFA Franc = 0.006212 Qatari Rial</inverseDescription>
	</item>
	<item>
		<title>1 QAR = 160.988759 XOF</title>
		<link>http://www.floatrates.com/qar/xof/</link>
		<description>1 Qatari Rial = 160.988759 West African CFA Franc</description>
		<pubDate></pubDate>
		<baseCurrency>QAR</baseCurrency>
		<baseName>Qatari Rial</baseName>
		<targetCurrency>XOF</targetCurrency>
		<targetName>West African CFA Franc</targetName>
		<exchangeRate>160.988759</exchangeRate>
		<inverseRate>0.006212</inverseRate>
		<inverseDescription>1 West African CFA Franc = 0.006212 Qatari Rial</inverseDescription>
	</item>
	<item>
		<title>1 QAR = 83.750000 NGN</title>
		<link>http://www.floatrates.com/qar/ngn/</link>
		<description>1 Qatari Rial = 83.750000 Nigerian Naira</description>
		<pubDate></pubDate>
		<baseCurrency>QAR</baseCurrency>
		<baseName>Qatari Rial</baseName>
		<targetCurrency>NGN</targetCurrency>
		<targetName>Nigerian Naira</targetName>
		<exchangeRate>83.750000</exchangeRate>
		<inverseRate>0.011940</inverseRate>
		<inverseDescription>1 Nigerian Naira = 0.011940 Qatari Rial</inverseDescription>
	</item>
	<item>
		<title>1 QAR = 13.013709 DOP</title>
		<link>http://www.floatrates.com/qar/dop/</link>
		<description>1 Qatari Rial = 13.013709 Dominican Peso</description>
		<pubDate></pubDate>
		<baseCurrency>QAR</baseCurrency>
		<baseName>Qatari Rial</baseName>
		<targetCurrency>DOP</targetCurrency>
		<targetName>Dominican Peso</targetName>
		<exchangeRate>13.013709</exchangeRate>
		<inverseRate>0.076842</inverseRate>
		<inverseDescription>1 Dominican Peso = 0.076842 Qatari Rial</inverseDescription>
	</item>
	<item>
		<title>1 QAR = 159.520604 CRC</title>
		<link>http://www.floatrates.com/qar/crc/</link>
		<description>1 Qatari Rial = 159.520604 Costa Rican Colón</description>
		<pubDate></pubDate>
		<baseCurrency>QAR</baseCurrency>
		<baseName>Qatari Rial</baseName>
		<targetCurrency>CRC</targetCurrency>
		<targetName>Costa Rican Colón</targetName>
		<exchangeRate>159.520604</exchangeRate>
		<inverseRate>0.006269</inverseRate>
		<inverseDescription>1 Costa Rican Colón = 0.006269 Qatari Rial</inverseDescription>
	</item>
</channel>

